vspyplugin/__init__.py
vspyplugin/__main__.py
vspyplugin/_metadata.py
vspyplugin/abstracts.py
vspyplugin/backends.py
vspyplugin/base.py
vspyplugin/cli.py
vspyplugin/cuda.py
vspyplugin/cupy.py
vspyplugin/cython.py
vspyplugin/exceptions.py
vspyplugin/numpy.py
vspyplugin/py.typed
vspyplugin/types.py
vspyplugin/utils.py
vspyplugin/coroutines/__init__.py
vspyplugin/coroutines/coros.py
vspyplugin/coroutines/frame_eval.py
vspyplugin/coroutines/funcs.py
vspyplugin/coroutines/types.py
vspyplugin-1.4.5.dist-info/licenses/LICENSE
vspyplugin-1.4.5.dist-info/METADATA
vspyplugin-1.4.5.dist-info/WHEEL
vspyplugin-1.4.5.dist-info/entry_points.txt
vspyplugin-1.4.5.dist-info/top_level.txt
vspyplugin-1.4.5.dist-info/RECORD
